README.md
setup.py
cobra2fn/__init__.py
cobra2fn/cobra2fn.py
cobra2fn.egg-info/PKG-INFO
cobra2fn.egg-info/SOURCES.txt
cobra2fn.egg-info/dependency_links.txt
cobra2fn.egg-info/top_level.txt