Metadata-Version: 1.0
Name: cobra2fn
Version: 0.1
Summary: Transform a cobra model into a flexible net
Home-page: https://bitbucket.org/Julvez/cobra2fn
Author: Jorge Julvez
Author-email: fnyzer@unizar.es
License: GNU GENERAL PUBLIC LICENSE
Keywords: cobra sbml flexible nets
Platform: UNKNOWN
